{
  "name": "services_v2",
  "base": "PersistedModel",
  "idInjection": true,
  "options": {
    "validateUpsert": true,
    "postgresql": {
      "schema": "public",
      "table": "historyshort"
    }
  },
  "properties": {
    "jobguid": {
      "type": "String",
      "id": 1,
      "required": true,
      "postgresql": {
        "columnName": "jobguid"
      }
    },
    "userId": {
      "type": "Number",
      "required": true,
      "postgresql": {
        "columnName": "customerid"
      }
    },
    "paytoolid": {
      "type": "Number",
      "required": false,
      "postgresql": {
        "columnName": "paytoolid"
      }
    },
    "amount": {
      "type": "Number",
      "required": false,
      "postgresql": {
        "columnName": "amount"
      }
    },
    "organisationid": {
      "type": "Number",
      "required": false,
      "postgresql": {
        "columnName": "organisationid"
      }
    },
    "orgId": {
      "type": "Number",
      "required": true,
      "postgresql": {
        "columnName": "srvcenterid"
      }
    },
    "orgName": {
      "type": "String",
      "required": true,
      "postgresql": {
        "columnName": "srvcenterdesc"
      }
    },
    "serviceid": {
      "type": "Number",
      "required": true,
      "postgresql": {
        "columnName": "serviceid"
      }
    },
    "serviceName": {
      "type": "String",
      "required": true,
      "postgresql": {
        "columnName": "servicedesc"
      }
    },
    "updatetime": {
      "type": "String",
      "required": false,
      "postgresql": {
        "columnName": "updatetime"
      }
    }
  },
  "validations": [],
  "relations": {},
  "acls": [],
  "methods": []
}
